MANIFEST.in
README.txt
setup.cfg
setup.py
collective/__init__.py
collective.mediaShow.egg-info/PKG-INFO
collective.mediaShow.egg-info/SOURCES.txt
collective.mediaShow.egg-info/dependency_links.txt
collective.mediaShow.egg-info/entry_points.txt
collective.mediaShow.egg-info/namespace_packages.txt
collective.mediaShow.egg-info/not-zip-safe
collective.mediaShow.egg-info/paster_plugins.txt
collective.mediaShow.egg-info/requires.txt
collective.mediaShow.egg-info/top_level.txt
collective/mediaShow/__init__.py
collective/mediaShow/configure.zcml
collective/mediaShow/profiles.zcml
collective/mediaShow/setuphandlers.py
collective/mediaShow/tests.py
collective/mediaShow/browser/__init__.py
collective/mediaShow/browser/configure.zcml
collective/mediaShow/browser/interfaces.py
collective/mediaShow/browser/mediaShow.py
collective/mediaShow/browser/mediaShowListing.pt
collective/mediaShow/browser/mediaShow_item.pt
collective/mediaShow/browser/views.py
collective/mediaShow/browser/images/ajax-loader.gif
collective/mediaShow/browser/images/buttons.png
collective/mediaShow/browser/images/stub.png
collective/mediaShow/browser/javascripts/jquery.touchwipe.min.js
collective/mediaShow/browser/javascripts/mediaShow.js
collective/mediaShow/browser/javascripts/youtube.js
collective/mediaShow/browser/stylesheets/fullscreen.css
collective/mediaShow/browser/stylesheets/mediaShow.css
collective/mediaShow/browser/stylesheets/presentationShow.css
collective/mediaShow/browser/templates/slideshow.pt
collective/mediaShow/profiles/default/browserlayer.xml
collective/mediaShow/profiles/default/collective.mediashow_various.txt
collective/mediaShow/profiles/default/cssregistry.xml
collective/mediaShow/profiles/default/jsregistry.xml
collective/mediaShow/profiles/default/metadata.xml
collective/mediaShow/profiles/default/tinymce.xml
collective/mediaShow/profiles/default/viewlets.xml
docs/HISTORY.txt
docs/INSTALL.txt
docs/LICENSE.GPL
docs/LICENSE.txt