Metadata-Version: 1.1
Name: collective.mediaShow
Version: 1.28
Summary: A flexible slideshow that can show any kind of media or Plone content
Home-page: https://github.com/intk/collective.mediaShow
Author: David Jonas, Andre Goncalves
Author-email: david@intk.com, andre@intk.com
License: GPL
Download-URL: https://github.com/intk/collective.mediaShow/tarball/1.28
Keywords: slideshow media video audio mediashow
Platform: UNKNOWN
Classifier: Framework :: Plone
Classifier: Programming Language :: Python
